public final class ady
  extends adh
{
  /* Error */
  public ady()
  {
    // Byte code:
    //   0: aload_0
    //   1: invokespecial 10	adh:<init>	()V
    //   4: aload_0
    //   5: sipush 128
    //   8: invokevirtual 14	ady:a	(I)V
    //   11: aload_0
    //   12: bipush 18
    //   14: invokevirtual 17	ady:b	(I)V
    //   17: ldc 19
    //   19: invokevirtual 25	java/lang/String:getBytes	()[B
    //   22: astore_1
    //   23: aload_0
    //   24: getfield 28	ady:a	Ladp;
    //   27: aload_1
    //   28: sipush 132
    //   31: invokevirtual 33	adp:a	([BI)V
    //   34: aload_0
    //   35: new 35	adf
    //   38: dup
    //   39: ldc 37
    //   41: invokevirtual 25	java/lang/String:getBytes	()[B
    //   44: invokespecial 40	adf:<init>	([B)V
    //   47: invokevirtual 43	ady:a	(Ladf;)V
    //   50: invokestatic 49	java/lang/System:currentTimeMillis	()J
    //   53: invokestatic 55	java/lang/Long:toHexString	(J)Ljava/lang/String;
    //   56: invokestatic 59	java/lang/String:valueOf	(Ljava/lang/Object;)Ljava/lang/String;
    //   59: astore_1
    //   60: aload_1
    //   61: invokevirtual 63	java/lang/String:length	()I
    //   64: ifeq +27 -> 91
    //   67: ldc 65
    //   69: aload_1
    //   70: invokevirtual 69	java/lang/String:concat	(Ljava/lang/String;)Ljava/lang/String;
    //   73: astore_1
    //   74: aload_1
    //   75: invokevirtual 25	java/lang/String:getBytes	()[B
    //   78: astore_1
    //   79: aload_0
    //   80: getfield 28	ady:a	Ladp;
    //   83: aload_1
    //   84: sipush 152
    //   87: invokevirtual 33	adp:a	([BI)V
    //   90: return
    //   91: new 21	java/lang/String
    //   94: dup
    //   95: ldc 65
    //   97: invokespecial 72	java/lang/String:<init>	(Ljava/lang/String;)V
    //   100: astore_1
    //   101: goto -27 -> 74
    //   104: astore_1
    //   105: ldc 74
    //   107: ldc 76
    //   109: aload_1
    //   110: invokestatic 82	android/util/Log:e	(Ljava/lang/String;Ljava/lang/String;Ljava/lang/Throwable;)I
    //   113: pop
    //   114: new 84	java/lang/RuntimeException
    //   117: dup
    //   118: aload_1
    //   119: invokespecial 87	java/lang/RuntimeException:<init>	(Ljava/lang/Throwable;)V
    //   122: athrow
    // Local variable table:
    //   start	length	slot	name	signature
    //   0	123	0	this	ady
    //   22	79	1	localObject	Object
    //   104	15	1	localadb	adb
    // Exception table:
    //   from	to	target	type
    //   4	74	104	adb
    //   74	90	104	adb
    //   91	101	104	adb
  }
  
  ady(adp paramadp, adj paramadj)
  {
    super(paramadp, paramadj);
  }
  
  public void a(adf[] paramArrayOfadf)
  {
    a.a(paramArrayOfadf);
  }
  
  public void b(long paramLong)
  {
    a.a(604800L, 136);
  }
  
  public void b(byte[] paramArrayOfByte)
  {
    a.a(paramArrayOfByte, 138);
  }
  
  public void c(long paramLong)
  {
    a.a(paramLong, 142);
  }
  
  public void e(int paramInt)
  {
    a.a(129, 134);
  }
  
  public long f()
  {
    return a.e(142);
  }
  
  public void f(int paramInt)
  {
    a.a(129, 144);
  }
}

/* Location:
 * Qualified Name:     ady
 * Java Class Version: 6 (50.0)
 * JD-Core Version:    0.7.1
 */