import android.text.TextUtils;
import java.io.IOException;
import java.util.Locale;
import java.util.regex.Matcher;
import java.util.regex.Pattern;

public final class aeg
{
  public static final char[] a;
  private static final String b;
  private static final Pattern c;
  
  static
  {
    Locale localLocale = Locale.getDefault();
    StringBuilder localStringBuilder = new StringBuilder();
    String str2 = localLocale.getLanguage();
    String str1;
    if (str2 == null) {
      str1 = null;
    }
    for (;;)
    {
      if (str1 != null)
      {
        localStringBuilder.append(str1);
        str1 = localLocale.getCountry();
        if (str1 != null)
        {
          localStringBuilder.append("-");
          localStringBuilder.append(str1);
        }
      }
      if (!Locale.US.equals(localLocale))
      {
        if (localStringBuilder.length() > 0) {
          localStringBuilder.append(", ");
        }
        localStringBuilder.append("en-US");
      }
      b = localStringBuilder.toString();
      c = Pattern.compile("##(\\S+)##");
      a = "0123456789ABCDEF".toCharArray();
      return;
      if ("iw".equals(str2))
      {
        str1 = "he";
      }
      else if ("in".equals(str2))
      {
        str1 = "id";
      }
      else
      {
        str1 = str2;
        if ("ji".equals(str2)) {
          str1 = "yi";
        }
      }
    }
  }
  
  private static String a(String paramString)
  {
    if (TextUtils.isEmpty(paramString)) {}
    Object localObject2;
    do
    {
      return paramString;
      Matcher localMatcher = c.matcher(paramString);
      int i = 0;
      Object localObject1;
      for (localObject2 = null; localMatcher.find(); localObject2 = localObject1)
      {
        localObject1 = localObject2;
        if (localObject2 == null) {
          localObject1 = new StringBuilder();
        }
        int j = localMatcher.start();
        if (j > i) {
          ((StringBuilder)localObject1).append(paramString.substring(i, j));
        }
        localObject2 = localMatcher.group(1);
        localObject2 = aei.a().b((String)localObject2);
        if (localObject2 != null) {
          ((StringBuilder)localObject1).append((String)localObject2);
        }
        i = localMatcher.end();
      }
      if ((localObject2 != null) && (i < paramString.length())) {
        ((StringBuilder)localObject2).append(paramString.substring(i));
      }
    } while (localObject2 == null);
    return ((StringBuilder)localObject2).toString();
  }
  
  private static void a(Exception paramException)
  {
    IOException localIOException = new IOException(paramException.getMessage());
    localIOException.initCause(paramException);
    throw localIOException;
  }
  
  /* Error */
  public static byte[] a(android.content.Context paramContext, String paramString1, byte[] paramArrayOfByte, int paramInt1, boolean paramBoolean1, String paramString2, int paramInt2, boolean paramBoolean2)
  {
    // Byte code:
    //   0: aload_1
    //   1: ifnonnull +13 -> 14
    //   4: new 154	java/lang/IllegalArgumentException
    //   7: dup
    //   8: ldc -98
    //   10: invokespecial 159	java/lang/IllegalArgumentException:<init>	(Ljava/lang/String;)V
    //   13: athrow
    //   14: new 161	java/net/URI
    //   17: dup
    //   18: aload_1
    //   19: invokespecial 162	java/net/URI:<init>	(Ljava/lang/String;)V
    //   22: astore 13
    //   24: new 164	org/apache/http/HttpHost
    //   27: dup
    //   28: aload 13
    //   30: invokevirtual 167	java/net/URI:getHost	()Ljava/lang/String;
    //   33: aload 13
    //   35: invokevirtual 170	java/net/URI:getPort	()I
    //   38: ldc -84
    //   40: invokespecial 175	org/apache/http/HttpHost:<init>	(Ljava/lang/String;ILjava/lang/String;)V
    //   43: astore 15
    //   45: invokestatic 124	aei:a	()Laei;
    //   48: invokevirtual 178	aei:g	()Ljava/lang/String;
    //   51: aload_0
    //   52: iload 7
    //   54: invokestatic 183	aej:a	(Ljava/lang/String;Landroid/content/Context;Z)Laej;
    //   57: astore 14
    //   59: aload 14
    //   61: invokevirtual 187	aej:getParams	()Lorg/apache/http/params/HttpParams;
    //   64: astore 13
    //   66: aload 13
    //   68: ldc -67
    //   70: invokestatic 195	org/apache/http/params/HttpProtocolParams:setContentCharset	(Lorg/apache/http/params/HttpParams;Ljava/lang/String;)V
    //   73: aload 13
    //   75: invokestatic 124	aei:a	()Laei;
    //   78: invokevirtual 198	aei:o	()I
    //   81: invokestatic 204	org/apache/http/params/HttpConnectionParams:setSoTimeout	(Lorg/apache/http/params/HttpParams;I)V
    //   84: iload_3
    //   85: tableswitch	default:+23->108, 1:+30->115, 2:+313->398
    //   108: aload 14
    //   110: invokevirtual 206	aej:a	()V
    //   113: aconst_null
    //   114: areturn
    //   115: aload 14
    //   117: astore 13
    //   119: new 208	aer
    //   122: dup
    //   123: aload_0
    //   124: ldc2_w 209
    //   127: aload_2
    //   128: invokespecial 213	aer:<init>	(Landroid/content/Context;J[B)V
    //   131: astore_0
    //   132: aload 14
    //   134: astore 13
    //   136: aload_0
    //   137: ldc -41
    //   139: invokevirtual 218	aer:setContentType	(Ljava/lang/String;)V
    //   142: aload 14
    //   144: astore 13
    //   146: new 220	org/apache/http/client/methods/HttpPost
    //   149: dup
    //   150: aload_1
    //   151: invokespecial 221	org/apache/http/client/methods/HttpPost:<init>	(Ljava/lang/String;)V
    //   154: astore_2
    //   155: aload 14
    //   157: astore 13
    //   159: aload_2
    //   160: aload_0
    //   161: invokevirtual 225	org/apache/http/client/methods/HttpPost:setEntity	(Lorg/apache/http/HttpEntity;)V
    //   164: aload 14
    //   166: astore 13
    //   168: aload 14
    //   170: invokevirtual 187	aej:getParams	()Lorg/apache/http/params/HttpParams;
    //   173: astore_0
    //   174: iload 4
    //   176: ifeq +22 -> 198
    //   179: aload 14
    //   181: astore 13
    //   183: aload_0
    //   184: new 164	org/apache/http/HttpHost
    //   187: dup
    //   188: aload 5
    //   190: iload 6
    //   192: invokespecial 228	org/apache/http/HttpHost:<init>	(Ljava/lang/String;I)V
    //   195: invokestatic 234	org/apache/http/conn/params/ConnRouteParams:setDefaultProxy	(Lorg/apache/http/params/HttpParams;Lorg/apache/http/HttpHost;)V
    //   198: aload 14
    //   200: astore 13
    //   202: aload_2
    //   203: aload_0
    //   204: invokeinterface 240 2 0
    //   209: aload 14
    //   211: astore 13
    //   213: aload_2
    //   214: ldc -14
    //   216: ldc -12
    //   218: invokeinterface 248 3 0
    //   223: aload 14
    //   225: astore 13
    //   227: invokestatic 124	aei:a	()Laei;
    //   230: invokevirtual 251	aei:h	()Ljava/lang/String;
    //   233: astore_0
    //   234: aload 14
    //   236: astore 13
    //   238: invokestatic 124	aei:a	()Laei;
    //   241: invokevirtual 254	aei:i	()Ljava/lang/String;
    //   244: astore_1
    //   245: aload_1
    //   246: ifnull +15 -> 261
    //   249: aload 14
    //   251: astore 13
    //   253: aload_2
    //   254: aload_0
    //   255: aload_1
    //   256: invokeinterface 248 3 0
    //   261: aload 14
    //   263: astore 13
    //   265: invokestatic 124	aei:a	()Laei;
    //   268: invokevirtual 257	aei:j	()Ljava/lang/String;
    //   271: astore_0
    //   272: aload_0
    //   273: ifnull +141 -> 414
    //   276: aload 14
    //   278: astore 13
    //   280: aload_0
    //   281: ldc_w 259
    //   284: invokevirtual 263	java/lang/String:split	(Ljava/lang/String;)[Ljava/lang/String;
    //   287: astore_0
    //   288: aload 14
    //   290: astore 13
    //   292: aload_0
    //   293: arraylength
    //   294: istore 6
    //   296: iconst_0
    //   297: istore_3
    //   298: iload_3
    //   299: iload 6
    //   301: if_icmpge +113 -> 414
    //   304: aload 14
    //   306: astore 13
    //   308: aload_0
    //   309: iload_3
    //   310: aaload
    //   311: ldc_w 265
    //   314: iconst_2
    //   315: invokevirtual 268	java/lang/String:split	(Ljava/lang/String;I)[Ljava/lang/String;
    //   318: astore 5
    //   320: aload 14
    //   322: astore 13
    //   324: aload 5
    //   326: arraylength
    //   327: iconst_2
    //   328: if_icmpne +835 -> 1163
    //   331: aload 14
    //   333: astore 13
    //   335: aload 5
    //   337: iconst_0
    //   338: aaload
    //   339: invokevirtual 271	java/lang/String:trim	()Ljava/lang/String;
    //   342: astore_1
    //   343: aload 14
    //   345: astore 13
    //   347: aload 5
    //   349: iconst_1
    //   350: aaload
    //   351: invokevirtual 271	java/lang/String:trim	()Ljava/lang/String;
    //   354: invokestatic 273	aeg:a	(Ljava/lang/String;)Ljava/lang/String;
    //   357: astore 5
    //   359: aload 14
    //   361: astore 13
    //   363: aload_1
    //   364: invokestatic 98	android/text/TextUtils:isEmpty	(Ljava/lang/CharSequence;)Z
    //   367: ifne +796 -> 1163
    //   370: aload 14
    //   372: astore 13
    //   374: aload 5
    //   376: invokestatic 98	android/text/TextUtils:isEmpty	(Ljava/lang/CharSequence;)Z
    //   379: ifne +784 -> 1163
    //   382: aload 14
    //   384: astore 13
    //   386: aload_2
    //   387: aload_1
    //   388: aload 5
    //   390: invokeinterface 248 3 0
    //   395: goto +768 -> 1163
    //   398: aload 14
    //   400: astore 13
    //   402: new 275	org/apache/http/client/methods/HttpGet
    //   405: dup
    //   406: aload_1
    //   407: invokespecial 276	org/apache/http/client/methods/HttpGet:<init>	(Ljava/lang/String;)V
    //   410: astore_2
    //   411: goto -247 -> 164
    //   414: aload 14
    //   416: astore 13
    //   418: aload_2
    //   419: ldc_w 278
    //   422: getstatic 57	aeg:b	Ljava/lang/String;
    //   425: invokeinterface 248 3 0
    //   430: aload 14
    //   432: astore 13
    //   434: aload 14
    //   436: aload 15
    //   438: aload_2
    //   439: invokevirtual 282	aej:execute	(Lorg/apache/http/HttpHost;Lorg/apache/http/HttpRequest;)Lorg/apache/http/HttpResponse;
    //   442: astore_0
    //   443: aload 14
    //   445: astore 13
    //   447: aload_0
    //   448: invokeinterface 288 1 0
    //   453: astore 15
    //   455: aload 14
    //   457: astore 13
    //   459: aload_0
    //   460: invokeinterface 292 1 0
    //   465: astore 5
    //   467: aconst_null
    //   468: astore_0
    //   469: aconst_null
    //   470: astore_1
    //   471: aload 5
    //   473: ifnull +246 -> 719
    //   476: aload_1
    //   477: astore_0
    //   478: aload 5
    //   480: invokeinterface 298 1 0
    //   485: lconst_0
    //   486: lcmp
    //   487: ifle +38 -> 525
    //   490: aload 5
    //   492: invokeinterface 298 1 0
    //   497: l2i
    //   498: newarray <illegal type>
    //   500: astore_0
    //   501: new 300	java/io/DataInputStream
    //   504: dup
    //   505: aload 5
    //   507: invokeinterface 304 1 0
    //   512: invokespecial 307	java/io/DataInputStream:<init>	(Ljava/io/InputStream;)V
    //   515: astore_1
    //   516: aload_1
    //   517: aload_0
    //   518: invokevirtual 311	java/io/DataInputStream:readFully	([B)V
    //   521: aload_1
    //   522: invokevirtual 314	java/io/DataInputStream:close	()V
    //   525: aload_0
    //   526: astore_1
    //   527: aload 5
    //   529: invokeinterface 317 1 0
    //   534: ifeq +165 -> 699
    //   537: invokestatic 124	aei:a	()Laei;
    //   540: invokevirtual 320	aei:e	()I
    //   543: istore 11
    //   545: iload 11
    //   547: newarray <illegal type>
    //   549: astore 16
    //   551: new 300	java/io/DataInputStream
    //   554: dup
    //   555: aload 5
    //   557: invokeinterface 304 1 0
    //   562: invokespecial 307	java/io/DataInputStream:<init>	(Ljava/io/InputStream;)V
    //   565: astore 13
    //   567: iconst_0
    //   568: istore_3
    //   569: iconst_0
    //   570: istore 8
    //   572: iconst_0
    //   573: istore 12
    //   575: aload 13
    //   577: aload 16
    //   579: iload 8
    //   581: iload 11
    //   583: invokevirtual 324	java/io/DataInputStream:read	([BII)I
    //   586: istore 6
    //   588: iload 8
    //   590: istore 9
    //   592: iload 11
    //   594: istore 10
    //   596: iload 6
    //   598: ifle +17 -> 615
    //   601: iload 11
    //   603: iload 6
    //   605: isub
    //   606: istore 10
    //   608: iload 8
    //   610: iload 6
    //   612: iadd
    //   613: istore 9
    //   615: iload 12
    //   617: istore 11
    //   619: iload 9
    //   621: istore 8
    //   623: iload 6
    //   625: istore_3
    //   626: iload 6
    //   628: iflt +30 -> 658
    //   631: iload 9
    //   633: istore 8
    //   635: iload 6
    //   637: istore_3
    //   638: iload 10
    //   640: istore 11
    //   642: iload 10
    //   644: ifgt -69 -> 575
    //   647: iload 6
    //   649: istore_3
    //   650: iload 9
    //   652: istore 8
    //   654: iload 12
    //   656: istore 11
    //   658: aload_0
    //   659: astore_1
    //   660: iload_3
    //   661: iconst_m1
    //   662: if_icmpne +32 -> 694
    //   665: aload_0
    //   666: astore_1
    //   667: iload 8
    //   669: ifle +25 -> 694
    //   672: aload_0
    //   673: astore_1
    //   674: iload 11
    //   676: ifne +18 -> 694
    //   679: iload 8
    //   681: newarray <illegal type>
    //   683: astore_1
    //   684: aload 16
    //   686: iconst_0
    //   687: aload_1
    //   688: iconst_0
    //   689: iload 8
    //   691: invokestatic 330	java/lang/System:arraycopy	(Ljava/lang/Object;ILjava/lang/Object;II)V
    //   694: aload 13
    //   696: invokevirtual 314	java/io/DataInputStream:close	()V
    //   699: aload_1
    //   700: astore_0
    //   701: aload 5
    //   703: ifnull +16 -> 719
    //   706: aload 14
    //   708: astore 13
    //   710: aload 5
    //   712: invokeinterface 333 1 0
    //   717: aload_1
    //   718: astore_0
    //   719: aload 14
    //   721: astore 13
    //   723: aload 15
    //   725: invokeinterface 338 1 0
    //   730: sipush 200
    //   733: if_icmpeq +308 -> 1041
    //   736: aload 14
    //   738: astore 13
    //   740: new 20	java/lang/StringBuilder
    //   743: dup
    //   744: invokespecial 23	java/lang/StringBuilder:<init>	()V
    //   747: astore_1
    //   748: aload_0
    //   749: ifnull +31 -> 780
    //   752: aload 14
    //   754: astore 13
    //   756: aload_1
    //   757: ldc_w 340
    //   760: invokevirtual 31	java/lang/StringBuilder:append	(Ljava/lang/String;)Ljava/lang/StringBuilder;
    //   763: new 71	java/lang/String
    //   766: dup
    //   767: aload_0
    //   768: invokespecial 342	java/lang/String:<init>	([B)V
    //   771: invokevirtual 31	java/lang/StringBuilder:append	(Ljava/lang/String;)Ljava/lang/StringBuilder;
    //   774: bipush 10
    //   776: invokevirtual 345	java/lang/StringBuilder:append	(C)Ljava/lang/StringBuilder;
    //   779: pop
    //   780: aload 14
    //   782: astore 13
    //   784: aload_2
    //   785: invokeinterface 349 1 0
    //   790: astore_0
    //   791: aload 14
    //   793: astore 13
    //   795: aload_0
    //   796: arraylength
    //   797: istore 6
    //   799: iconst_0
    //   800: istore_3
    //   801: iload_3
    //   802: iload 6
    //   804: if_icmpge +124 -> 928
    //   807: aload_0
    //   808: iload_3
    //   809: aaload
    //   810: astore_2
    //   811: aload_2
    //   812: ifnull +43 -> 855
    //   815: aload 14
    //   817: astore 13
    //   819: aload_1
    //   820: ldc_w 351
    //   823: invokevirtual 31	java/lang/StringBuilder:append	(Ljava/lang/String;)Ljava/lang/StringBuilder;
    //   826: aload_2
    //   827: invokeinterface 356 1 0
    //   832: invokevirtual 31	java/lang/StringBuilder:append	(Ljava/lang/String;)Ljava/lang/StringBuilder;
    //   835: bipush 61
    //   837: invokevirtual 345	java/lang/StringBuilder:append	(C)Ljava/lang/StringBuilder;
    //   840: aload_2
    //   841: invokeinterface 359 1 0
    //   846: invokevirtual 31	java/lang/StringBuilder:append	(Ljava/lang/String;)Ljava/lang/StringBuilder;
    //   849: bipush 10
    //   851: invokevirtual 345	java/lang/StringBuilder:append	(C)Ljava/lang/StringBuilder;
    //   854: pop
    //   855: iload_3
    //   856: iconst_1
    //   857: iadd
    //   858: istore_3
    //   859: goto -58 -> 801
    //   862: astore_0
    //   863: aload_1
    //   864: invokevirtual 314	java/io/DataInputStream:close	()V
    //   867: aload_0
    //   868: athrow
    //   869: astore_0
    //   870: aload 5
    //   872: ifnull +14 -> 886
    //   875: aload 14
    //   877: astore 13
    //   879: aload 5
    //   881: invokeinterface 333 1 0
    //   886: aload 14
    //   888: astore 13
    //   890: aload_0
    //   891: athrow
    //   892: astore_0
    //   893: aload 14
    //   895: astore 13
    //   897: aload_0
    //   898: invokestatic 361	aeg:a	(Ljava/lang/Exception;)V
    //   901: aload 14
    //   903: ifnull +8 -> 911
    //   906: aload 14
    //   908: invokevirtual 206	aej:a	()V
    //   911: aconst_null
    //   912: areturn
    //   913: astore_1
    //   914: iconst_1
    //   915: istore 11
    //   917: goto -259 -> 658
    //   920: astore_0
    //   921: aload 13
    //   923: invokevirtual 314	java/io/DataInputStream:close	()V
    //   926: aload_0
    //   927: athrow
    //   928: aload 14
    //   930: astore 13
    //   932: aload 15
    //   934: invokeinterface 364 1 0
    //   939: invokestatic 368	java/lang/String:valueOf	(Ljava/lang/Object;)Ljava/lang/String;
    //   942: astore_0
    //   943: aload 14
    //   945: astore 13
    //   947: aload_0
    //   948: invokevirtual 130	java/lang/String:length	()I
    //   951: ifeq +50 -> 1001
    //   954: aload 14
    //   956: astore 13
    //   958: ldc_w 370
    //   961: aload_0
    //   962: invokevirtual 373	java/lang/String:concat	(Ljava/lang/String;)Ljava/lang/String;
    //   965: astore_0
    //   966: aload 14
    //   968: astore 13
    //   970: new 135	java/io/IOException
    //   973: dup
    //   974: aload_0
    //   975: invokespecial 143	java/io/IOException:<init>	(Ljava/lang/String;)V
    //   978: athrow
    //   979: astore_0
    //   980: aload 14
    //   982: astore 13
    //   984: aload_0
    //   985: invokestatic 361	aeg:a	(Ljava/lang/Exception;)V
    //   988: aload 14
    //   990: ifnull -79 -> 911
    //   993: aload 14
    //   995: invokevirtual 206	aej:a	()V
    //   998: goto -87 -> 911
    //   1001: aload 14
    //   1003: astore 13
    //   1005: new 71	java/lang/String
    //   1008: dup
    //   1009: ldc_w 370
    //   1012: invokespecial 374	java/lang/String:<init>	(Ljava/lang/String;)V
    //   1015: astore_0
    //   1016: goto -50 -> 966
    //   1019: astore_0
    //   1020: aload 14
    //   1022: astore 13
    //   1024: aload_0
    //   1025: invokestatic 361	aeg:a	(Ljava/lang/Exception;)V
    //   1028: aload 14
    //   1030: ifnull -119 -> 911
    //   1033: aload 14
    //   1035: invokevirtual 206	aej:a	()V
    //   1038: goto -127 -> 911
    //   1041: aload 14
    //   1043: invokevirtual 206	aej:a	()V
    //   1046: aload_0
    //   1047: areturn
    //   1048: astore_0
    //   1049: aconst_null
    //   1050: astore 14
    //   1052: aload 14
    //   1054: astore 13
    //   1056: aload_0
    //   1057: invokestatic 361	aeg:a	(Ljava/lang/Exception;)V
    //   1060: aload 14
    //   1062: ifnull -151 -> 911
    //   1065: aload 14
    //   1067: invokevirtual 206	aej:a	()V
    //   1070: goto -159 -> 911
    //   1073: astore_0
    //   1074: aconst_null
    //   1075: astore 14
    //   1077: aload 14
    //   1079: astore 13
    //   1081: aload_0
    //   1082: invokestatic 361	aeg:a	(Ljava/lang/Exception;)V
    //   1085: aload 14
    //   1087: ifnull -176 -> 911
    //   1090: aload 14
    //   1092: invokevirtual 206	aej:a	()V
    //   1095: goto -184 -> 911
    //   1098: astore_0
    //   1099: aconst_null
    //   1100: astore 13
    //   1102: aload 13
    //   1104: ifnull +8 -> 1112
    //   1107: aload 13
    //   1109: invokevirtual 206	aej:a	()V
    //   1112: aload_0
    //   1113: athrow
    //   1114: astore_1
    //   1115: goto -590 -> 525
    //   1118: astore_1
    //   1119: goto -252 -> 867
    //   1122: astore_0
    //   1123: goto -424 -> 699
    //   1126: astore_1
    //   1127: goto -201 -> 926
    //   1130: astore_0
    //   1131: goto -29 -> 1102
    //   1134: astore_0
    //   1135: goto -58 -> 1077
    //   1138: astore_0
    //   1139: goto -87 -> 1052
    //   1142: astore_0
    //   1143: aconst_null
    //   1144: astore 14
    //   1146: goto -126 -> 1020
    //   1149: astore_0
    //   1150: aconst_null
    //   1151: astore 14
    //   1153: goto -173 -> 980
    //   1156: astore_0
    //   1157: aconst_null
    //   1158: astore 14
    //   1160: goto -267 -> 893
    //   1163: iload_3
    //   1164: iconst_1
    //   1165: iadd
    //   1166: istore_3
    //   1167: goto -869 -> 298
    // Local variable table:
    //   start	length	slot	name	signature
    //   0	1170	0	paramContext	android.content.Context
    //   0	1170	1	paramString1	String
    //   0	1170	2	paramArrayOfByte	byte[]
    //   0	1170	3	paramInt1	int
    //   0	1170	4	paramBoolean1	boolean
    //   0	1170	5	paramString2	String
    //   0	1170	6	paramInt2	int
    //   0	1170	7	paramBoolean2	boolean
    //   570	120	8	i	int
    //   590	61	9	j	int
    //   594	49	10	k	int
    //   543	373	11	m	int
    //   573	82	12	n	int
    //   22	1086	13	localObject1	Object
    //   57	1102	14	localaej	aej
    //   43	890	15	localObject2	Object
    //   549	136	16	arrayOfByte	byte[]
    // Exception table:
    //   from	to	target	type
    //   516	521	862	finally
    //   478	516	869	finally
    //   521	525	869	finally
    //   527	567	869	finally
    //   694	699	869	finally
    //   863	867	869	finally
    //   867	869	869	finally
    //   921	926	869	finally
    //   926	928	869	finally
    //   119	132	892	java/net/URISyntaxException
    //   136	142	892	java/net/URISyntaxException
    //   146	155	892	java/net/URISyntaxException
    //   159	164	892	java/net/URISyntaxException
    //   168	174	892	java/net/URISyntaxException
    //   183	198	892	java/net/URISyntaxException
    //   202	209	892	java/net/URISyntaxException
    //   213	223	892	java/net/URISyntaxException
    //   227	234	892	java/net/URISyntaxException
    //   238	245	892	java/net/URISyntaxException
    //   253	261	892	java/net/URISyntaxException
    //   265	272	892	java/net/URISyntaxException
    //   280	288	892	java/net/URISyntaxException
    //   292	296	892	java/net/URISyntaxException
    //   308	320	892	java/net/URISyntaxException
    //   324	331	892	java/net/URISyntaxException
    //   335	343	892	java/net/URISyntaxException
    //   347	359	892	java/net/URISyntaxException
    //   363	370	892	java/net/URISyntaxException
    //   374	382	892	java/net/URISyntaxException
    //   386	395	892	java/net/URISyntaxException
    //   402	411	892	java/net/URISyntaxException
    //   418	430	892	java/net/URISyntaxException
    //   434	443	892	java/net/URISyntaxException
    //   447	455	892	java/net/URISyntaxException
    //   459	467	892	java/net/URISyntaxException
    //   710	717	892	java/net/URISyntaxException
    //   723	736	892	java/net/URISyntaxException
    //   740	748	892	java/net/URISyntaxException
    //   756	780	892	java/net/URISyntaxException
    //   784	791	892	java/net/URISyntaxException
    //   795	799	892	java/net/URISyntaxException
    //   819	855	892	java/net/URISyntaxException
    //   879	886	892	java/net/URISyntaxException
    //   890	892	892	java/net/URISyntaxException
    //   932	943	892	java/net/URISyntaxException
    //   947	954	892	java/net/URISyntaxException
    //   958	966	892	java/net/URISyntaxException
    //   970	979	892	java/net/URISyntaxException
    //   1005	1016	892	java/net/URISyntaxException
    //   575	588	913	java/io/IOException
    //   575	588	920	finally
    //   679	694	920	finally
    //   119	132	979	java/lang/IllegalStateException
    //   136	142	979	java/lang/IllegalStateException
    //   146	155	979	java/lang/IllegalStateException
    //   159	164	979	java/lang/IllegalStateException
    //   168	174	979	java/lang/IllegalStateException
    //   183	198	979	java/lang/IllegalStateException
    //   202	209	979	java/lang/IllegalStateException
    //   213	223	979	java/lang/IllegalStateException
    //   227	234	979	java/lang/IllegalStateException
    //   238	245	979	java/lang/IllegalStateException
    //   253	261	979	java/lang/IllegalStateException
    //   265	272	979	java/lang/IllegalStateException
    //   280	288	979	java/lang/IllegalStateException
    //   292	296	979	java/lang/IllegalStateException
    //   308	320	979	java/lang/IllegalStateException
    //   324	331	979	java/lang/IllegalStateException
    //   335	343	979	java/lang/IllegalStateException
    //   347	359	979	java/lang/IllegalStateException
    //   363	370	979	java/lang/IllegalStateException
    //   374	382	979	java/lang/IllegalStateException
    //   386	395	979	java/lang/IllegalStateException
    //   402	411	979	java/lang/IllegalStateException
    //   418	430	979	java/lang/IllegalStateException
    //   434	443	979	java/lang/IllegalStateException
    //   447	455	979	java/lang/IllegalStateException
    //   459	467	979	java/lang/IllegalStateException
    //   710	717	979	java/lang/IllegalStateException
    //   723	736	979	java/lang/IllegalStateException
    //   740	748	979	java/lang/IllegalStateException
    //   756	780	979	java/lang/IllegalStateException
    //   784	791	979	java/lang/IllegalStateException
    //   795	799	979	java/lang/IllegalStateException
    //   819	855	979	java/lang/IllegalStateException
    //   879	886	979	java/lang/IllegalStateException
    //   890	892	979	java/lang/IllegalStateException
    //   932	943	979	java/lang/IllegalStateException
    //   947	954	979	java/lang/IllegalStateException
    //   958	966	979	java/lang/IllegalStateException
    //   970	979	979	java/lang/IllegalStateException
    //   1005	1016	979	java/lang/IllegalStateException
    //   119	132	1019	java/lang/IllegalArgumentException
    //   136	142	1019	java/lang/IllegalArgumentException
    //   146	155	1019	java/lang/IllegalArgumentException
    //   159	164	1019	java/lang/IllegalArgumentException
    //   168	174	1019	java/lang/IllegalArgumentException
    //   183	198	1019	java/lang/IllegalArgumentException
    //   202	209	1019	java/lang/IllegalArgumentException
    //   213	223	1019	java/lang/IllegalArgumentException
    //   227	234	1019	java/lang/IllegalArgumentException
    //   238	245	1019	java/lang/IllegalArgumentException
    //   253	261	1019	java/lang/IllegalArgumentException
    //   265	272	1019	java/lang/IllegalArgumentException
    //   280	288	1019	java/lang/IllegalArgumentException
    //   292	296	1019	java/lang/IllegalArgumentException
    //   308	320	1019	java/lang/IllegalArgumentException
    //   324	331	1019	java/lang/IllegalArgumentException
    //   335	343	1019	java/lang/IllegalArgumentException
    //   347	359	1019	java/lang/IllegalArgumentException
    //   363	370	1019	java/lang/IllegalArgumentException
    //   374	382	1019	java/lang/IllegalArgumentException
    //   386	395	1019	java/lang/IllegalArgumentException
    //   402	411	1019	java/lang/IllegalArgumentException
    //   418	430	1019	java/lang/IllegalArgumentException
    //   434	443	1019	java/lang/IllegalArgumentException
    //   447	455	1019	java/lang/IllegalArgumentException
    //   459	467	1019	java/lang/IllegalArgumentException
    //   710	717	1019	java/lang/IllegalArgumentException
    //   723	736	1019	java/lang/IllegalArgumentException
    //   740	748	1019	java/lang/IllegalArgumentException
    //   756	780	1019	java/lang/IllegalArgumentException
    //   784	791	1019	java/lang/IllegalArgumentException
    //   795	799	1019	java/lang/IllegalArgumentException
    //   819	855	1019	java/lang/IllegalArgumentException
    //   879	886	1019	java/lang/IllegalArgumentException
    //   890	892	1019	java/lang/IllegalArgumentException
    //   932	943	1019	java/lang/IllegalArgumentException
    //   947	954	1019	java/lang/IllegalArgumentException
    //   958	966	1019	java/lang/IllegalArgumentException
    //   970	979	1019	java/lang/IllegalArgumentException
    //   1005	1016	1019	java/lang/IllegalArgumentException
    //   14	84	1048	java/net/SocketException
    //   14	84	1073	java/lang/Exception
    //   14	84	1098	finally
    //   521	525	1114	java/io/IOException
    //   863	867	1118	java/io/IOException
    //   694	699	1122	java/io/IOException
    //   921	926	1126	java/io/IOException
    //   119	132	1130	finally
    //   136	142	1130	finally
    //   146	155	1130	finally
    //   159	164	1130	finally
    //   168	174	1130	finally
    //   183	198	1130	finally
    //   202	209	1130	finally
    //   213	223	1130	finally
    //   227	234	1130	finally
    //   238	245	1130	finally
    //   253	261	1130	finally
    //   265	272	1130	finally
    //   280	288	1130	finally
    //   292	296	1130	finally
    //   308	320	1130	finally
    //   324	331	1130	finally
    //   335	343	1130	finally
    //   347	359	1130	finally
    //   363	370	1130	finally
    //   374	382	1130	finally
    //   386	395	1130	finally
    //   402	411	1130	finally
    //   418	430	1130	finally
    //   434	443	1130	finally
    //   447	455	1130	finally
    //   459	467	1130	finally
    //   710	717	1130	finally
    //   723	736	1130	finally
    //   740	748	1130	finally
    //   756	780	1130	finally
    //   784	791	1130	finally
    //   795	799	1130	finally
    //   819	855	1130	finally
    //   879	886	1130	finally
    //   890	892	1130	finally
    //   897	901	1130	finally
    //   932	943	1130	finally
    //   947	954	1130	finally
    //   958	966	1130	finally
    //   970	979	1130	finally
    //   984	988	1130	finally
    //   1005	1016	1130	finally
    //   1024	1028	1130	finally
    //   1056	1060	1130	finally
    //   1081	1085	1130	finally
    //   119	132	1134	java/lang/Exception
    //   136	142	1134	java/lang/Exception
    //   146	155	1134	java/lang/Exception
    //   159	164	1134	java/lang/Exception
    //   168	174	1134	java/lang/Exception
    //   183	198	1134	java/lang/Exception
    //   202	209	1134	java/lang/Exception
    //   213	223	1134	java/lang/Exception
    //   227	234	1134	java/lang/Exception
    //   238	245	1134	java/lang/Exception
    //   253	261	1134	java/lang/Exception
    //   265	272	1134	java/lang/Exception
    //   280	288	1134	java/lang/Exception
    //   292	296	1134	java/lang/Exception
    //   308	320	1134	java/lang/Exception
    //   324	331	1134	java/lang/Exception
    //   335	343	1134	java/lang/Exception
    //   347	359	1134	java/lang/Exception
    //   363	370	1134	java/lang/Exception
    //   374	382	1134	java/lang/Exception
    //   386	395	1134	java/lang/Exception
    //   402	411	1134	java/lang/Exception
    //   418	430	1134	java/lang/Exception
    //   434	443	1134	java/lang/Exception
    //   447	455	1134	java/lang/Exception
    //   459	467	1134	java/lang/Exception
    //   710	717	1134	java/lang/Exception
    //   723	736	1134	java/lang/Exception
    //   740	748	1134	java/lang/Exception
    //   756	780	1134	java/lang/Exception
    //   784	791	1134	java/lang/Exception
    //   795	799	1134	java/lang/Exception
    //   819	855	1134	java/lang/Exception
    //   879	886	1134	java/lang/Exception
    //   890	892	1134	java/lang/Exception
    //   932	943	1134	java/lang/Exception
    //   947	954	1134	java/lang/Exception
    //   958	966	1134	java/lang/Exception
    //   970	979	1134	java/lang/Exception
    //   1005	1016	1134	java/lang/Exception
    //   119	132	1138	java/net/SocketException
    //   136	142	1138	java/net/SocketException
    //   146	155	1138	java/net/SocketException
    //   159	164	1138	java/net/SocketException
    //   168	174	1138	java/net/SocketException
    //   183	198	1138	java/net/SocketException
    //   202	209	1138	java/net/SocketException
    //   213	223	1138	java/net/SocketException
    //   227	234	1138	java/net/SocketException
    //   238	245	1138	java/net/SocketException
    //   253	261	1138	java/net/SocketException
    //   265	272	1138	java/net/SocketException
    //   280	288	1138	java/net/SocketException
    //   292	296	1138	java/net/SocketException
    //   308	320	1138	java/net/SocketException
    //   324	331	1138	java/net/SocketException
    //   335	343	1138	java/net/SocketException
    //   347	359	1138	java/net/SocketException
    //   363	370	1138	java/net/SocketException
    //   374	382	1138	java/net/SocketException
    //   386	395	1138	java/net/SocketException
    //   402	411	1138	java/net/SocketException
    //   418	430	1138	java/net/SocketException
    //   434	443	1138	java/net/SocketException
    //   447	455	1138	java/net/SocketException
    //   459	467	1138	java/net/SocketException
    //   710	717	1138	java/net/SocketException
    //   723	736	1138	java/net/SocketException
    //   740	748	1138	java/net/SocketException
    //   756	780	1138	java/net/SocketException
    //   784	791	1138	java/net/SocketException
    //   795	799	1138	java/net/SocketException
    //   819	855	1138	java/net/SocketException
    //   879	886	1138	java/net/SocketException
    //   890	892	1138	java/net/SocketException
    //   932	943	1138	java/net/SocketException
    //   947	954	1138	java/net/SocketException
    //   958	966	1138	java/net/SocketException
    //   970	979	1138	java/net/SocketException
    //   1005	1016	1138	java/net/SocketException
    //   14	84	1142	java/lang/IllegalArgumentException
    //   14	84	1149	java/lang/IllegalStateException
    //   14	84	1156	java/net/URISyntaxException
  }
}

/* Location:
 * Qualified Name:     aeg
 * Java Class Version: 6 (50.0)
 * JD-Core Version:    0.7.1
 */