import android.content.Context;

public final class bdc
  implements Runnable
{
  private static final ezv a = ezv.a("concurrent");
  private final bdm b;
  private final Context c;
  
  public bdc(Context paramContext, bdm parambdm)
  {
    c = paramContext;
    b = parambdm;
  }
  
  /* Error */
  public void run()
  {
    // Byte code:
    //   0: aload_0
    //   1: getfield 32	bdc:b	Lbdm;
    //   4: invokevirtual 40	bdm:a	()Lbcp;
    //   7: astore 5
    //   9: aload 5
    //   11: ifnonnull +4 -> 15
    //   14: return
    //   15: aload 5
    //   17: invokevirtual 45	bcp:a	()Ljava/lang/String;
    //   20: astore_3
    //   21: getstatic 23	bdc:a	Lezv;
    //   24: astore 4
    //   26: ldc 47
    //   28: invokestatic 53	java/lang/String:valueOf	(Ljava/lang/Object;)Ljava/lang/String;
    //   31: astore_2
    //   32: aload_3
    //   33: invokestatic 53	java/lang/String:valueOf	(Ljava/lang/Object;)Ljava/lang/String;
    //   36: astore 6
    //   38: aload 6
    //   40: invokevirtual 57	java/lang/String:length	()I
    //   43: ifeq +220 -> 263
    //   46: aload_2
    //   47: aload 6
    //   49: invokevirtual 61	java/lang/String:concat	(Ljava/lang/String;)Ljava/lang/String;
    //   52: astore_2
    //   53: aload 4
    //   55: aload_2
    //   56: invokevirtual 63	ezv:b	(Ljava/lang/String;)Ljava/lang/String;
    //   59: astore 4
    //   61: aload_0
    //   62: getfield 32	bdc:b	Lbdm;
    //   65: aload 5
    //   67: getfield 66	bcp:a	Ljava/lang/String;
    //   70: invokevirtual 69	bdm:a	(Ljava/lang/String;)Ljava/lang/Class;
    //   73: astore_2
    //   74: aload_3
    //   75: invokestatic 53	java/lang/String:valueOf	(Ljava/lang/Object;)Ljava/lang/String;
    //   78: astore 6
    //   80: aload 6
    //   82: invokevirtual 57	java/lang/String:length	()I
    //   85: ifeq +190 -> 275
    //   88: ldc 71
    //   90: aload 6
    //   92: invokevirtual 61	java/lang/String:concat	(Ljava/lang/String;)Ljava/lang/String;
    //   95: pop
    //   96: aload 5
    //   98: aload_2
    //   99: invokevirtual 74	bcp:a	(Ljava/lang/Class;)Lbcn;
    //   102: astore 6
    //   104: aload 6
    //   106: aload_0
    //   107: getfield 30	bdc:c	Landroid/content/Context;
    //   110: aload 5
    //   112: getfield 77	bcp:c	Lbcg;
    //   115: invokeinterface 82 3 0
    //   120: istore_1
    //   121: aload_0
    //   122: getfield 32	bdc:b	Lbdm;
    //   125: astore_2
    //   126: aload_2
    //   127: monitorenter
    //   128: aload 5
    //   130: iconst_0
    //   131: putfield 86	bcp:f	Z
    //   134: getstatic 91	bdd:a	[I
    //   137: iload_1
    //   138: iconst_1
    //   139: isub
    //   140: iaload
    //   141: tableswitch	default:+285->426, 1:+147->288, 2:+208->349, 3:+235->376, 4:+247->388
    //   172: new 93	java/lang/IllegalArgumentException
    //   175: dup
    //   176: ldc 95
    //   178: invokespecial 98	java/lang/IllegalArgumentException:<init>	(Ljava/lang/String;)V
    //   181: athrow
    //   182: astore 5
    //   184: aload_2
    //   185: monitorexit
    //   186: aload 5
    //   188: athrow
    //   189: astore 5
    //   191: aload_3
    //   192: invokestatic 53	java/lang/String:valueOf	(Ljava/lang/Object;)Ljava/lang/String;
    //   195: astore_2
    //   196: aload_2
    //   197: invokevirtual 57	java/lang/String:length	()I
    //   200: ifeq +200 -> 400
    //   203: ldc 100
    //   205: aload_2
    //   206: invokevirtual 61	java/lang/String:concat	(Ljava/lang/String;)Ljava/lang/String;
    //   209: astore_2
    //   210: ldc 102
    //   212: aload_2
    //   213: aload 5
    //   215: invokestatic 108	android/util/Log:e	(Ljava/lang/String;Ljava/lang/String;Ljava/lang/Throwable;)I
    //   218: pop
    //   219: getstatic 23	bdc:a	Lezv;
    //   222: astore 6
    //   224: aload_3
    //   225: invokestatic 53	java/lang/String:valueOf	(Ljava/lang/Object;)Ljava/lang/String;
    //   228: astore_2
    //   229: aload_2
    //   230: invokevirtual 57	java/lang/String:length	()I
    //   233: ifeq +180 -> 413
    //   236: ldc 110
    //   238: aload_2
    //   239: invokevirtual 61	java/lang/String:concat	(Ljava/lang/String;)Ljava/lang/String;
    //   242: astore_2
    //   243: aload 6
    //   245: aload_2
    //   246: invokevirtual 113	ezv:d	(Ljava/lang/String;)V
    //   249: aload 5
    //   251: athrow
    //   252: astore_2
    //   253: getstatic 23	bdc:a	Lezv;
    //   256: aload 4
    //   258: invokevirtual 115	ezv:c	(Ljava/lang/String;)V
    //   261: aload_2
    //   262: athrow
    //   263: new 49	java/lang/String
    //   266: dup
    //   267: aload_2
    //   268: invokespecial 116	java/lang/String:<init>	(Ljava/lang/String;)V
    //   271: astore_2
    //   272: goto -219 -> 53
    //   275: new 49	java/lang/String
    //   278: dup
    //   279: ldc 71
    //   281: invokespecial 116	java/lang/String:<init>	(Ljava/lang/String;)V
    //   284: pop
    //   285: goto -189 -> 96
    //   288: aload_0
    //   289: getfield 32	bdc:b	Lbdm;
    //   292: aload 5
    //   294: invokevirtual 119	bdm:a	(Lbcp;)V
    //   297: aload 5
    //   299: invokevirtual 45	bcp:a	()Ljava/lang/String;
    //   302: invokestatic 53	java/lang/String:valueOf	(Ljava/lang/Object;)Ljava/lang/String;
    //   305: astore 5
    //   307: aload 5
    //   309: invokevirtual 57	java/lang/String:length	()I
    //   312: ifeq +24 -> 336
    //   315: ldc 121
    //   317: aload 5
    //   319: invokevirtual 61	java/lang/String:concat	(Ljava/lang/String;)Ljava/lang/String;
    //   322: pop
    //   323: aload_2
    //   324: monitorexit
    //   325: getstatic 23	bdc:a	Lezv;
    //   328: aload 4
    //   330: invokevirtual 115	ezv:c	(Ljava/lang/String;)V
    //   333: goto -333 -> 0
    //   336: new 49	java/lang/String
    //   339: dup
    //   340: ldc 121
    //   342: invokespecial 116	java/lang/String:<init>	(Ljava/lang/String;)V
    //   345: pop
    //   346: goto -23 -> 323
    //   349: aload_0
    //   350: getfield 32	bdc:b	Lbdm;
    //   353: aload 5
    //   355: invokevirtual 119	bdm:a	(Lbcp;)V
    //   358: aload_0
    //   359: getfield 32	bdc:b	Lbdm;
    //   362: aload 6
    //   364: lconst_0
    //   365: invokestatic 126	bcx:b	(Lbcn;J)Lbcp;
    //   368: iconst_1
    //   369: invokevirtual 129	bdm:a	(Lbcp;Z)Z
    //   372: pop
    //   373: goto -50 -> 323
    //   376: aload_0
    //   377: getfield 32	bdc:b	Lbdm;
    //   380: aload 5
    //   382: invokevirtual 119	bdm:a	(Lbcp;)V
    //   385: goto -62 -> 323
    //   388: aload_0
    //   389: getfield 32	bdc:b	Lbdm;
    //   392: aload 5
    //   394: invokevirtual 131	bdm:b	(Lbcp;)V
    //   397: goto -74 -> 323
    //   400: new 49	java/lang/String
    //   403: dup
    //   404: ldc 100
    //   406: invokespecial 116	java/lang/String:<init>	(Ljava/lang/String;)V
    //   409: astore_2
    //   410: goto -200 -> 210
    //   413: new 49	java/lang/String
    //   416: dup
    //   417: ldc 110
    //   419: invokespecial 116	java/lang/String:<init>	(Ljava/lang/String;)V
    //   422: astore_2
    //   423: goto -180 -> 243
    //   426: goto -254 -> 172
    // Local variable table:
    //   start	length	slot	name	signature
    //   0	429	0	this	bdc
    //   120	20	1	i	int
    //   252	16	2	str1	String
    //   271	152	2	str2	String
    //   20	205	3	str3	String
    //   24	305	4	localObject2	Object
    //   7	122	5	localbcp	bcp
    //   182	5	5	localObject3	Object
    //   189	109	5	localException	Exception
    //   305	88	5	str4	String
    //   36	327	6	localObject4	Object
    // Exception table:
    //   from	to	target	type
    //   128	172	182	finally
    //   172	182	182	finally
    //   184	186	182	finally
    //   288	323	182	finally
    //   323	325	182	finally
    //   336	346	182	finally
    //   349	373	182	finally
    //   376	385	182	finally
    //   388	397	182	finally
    //   61	96	189	java/lang/Exception
    //   96	128	189	java/lang/Exception
    //   186	189	189	java/lang/Exception
    //   275	285	189	java/lang/Exception
    //   61	96	252	finally
    //   96	128	252	finally
    //   186	189	252	finally
    //   191	210	252	finally
    //   210	243	252	finally
    //   243	252	252	finally
    //   275	285	252	finally
    //   400	410	252	finally
    //   413	423	252	finally
  }
}

/* Location:
 * Qualified Name:     bdc
 * Java Class Version: 6 (50.0)
 * JD-Core Version:    0.7.1
 */