public final class dyh
  extends dyx
{
  private final int a;
  private final String e;
  
  public dyh(bfd parambfd, String paramString, int paramInt)
  {
    super(parambfd);
    e = paramString;
    a = paramInt;
  }
  
  /* Error */
  public void p_()
  {
    // Byte code:
    //   0: ldc 22
    //   2: iconst_3
    //   3: invokestatic 27	ezi:a	(Ljava/lang/String;I)Z
    //   6: ifeq +35 -> 41
    //   9: aload_0
    //   10: getfield 15	dyh:e	Ljava/lang/String;
    //   13: invokestatic 33	java/lang/String:valueOf	(Ljava/lang/Object;)Ljava/lang/String;
    //   16: astore_3
    //   17: aload_3
    //   18: invokevirtual 37	java/lang/String:length	()I
    //   21: ifeq +152 -> 173
    //   24: ldc 39
    //   26: aload_3
    //   27: invokevirtual 43	java/lang/String:concat	(Ljava/lang/String;)Ljava/lang/String;
    //   30: astore_3
    //   31: ldc 22
    //   33: aload_3
    //   34: iconst_0
    //   35: anewarray 45	java/lang/Object
    //   38: invokestatic 48	ezi:a	(Ljava/lang/String;Ljava/lang/String;[Ljava/lang/Object;)V
    //   41: invokestatic 54	bfz:i	()Ljava/lang/String;
    //   44: astore 4
    //   46: new 50	bfz
    //   49: dup
    //   50: getstatic 60	aal:oJ	Landroid/content/Context;
    //   53: aload_0
    //   54: getfield 64	dyx:b	Ldvb;
    //   57: getfield 67	dvb:a	I
    //   60: invokespecial 70	bfz:<init>	(Landroid/content/Context;I)V
    //   63: astore_3
    //   64: aload_3
    //   65: invokevirtual 72	bfz:a	()V
    //   68: aload_3
    //   69: aload_0
    //   70: getfield 15	dyh:e	Ljava/lang/String;
    //   73: invokevirtual 76	bfz:y	(Ljava/lang/String;)I
    //   76: pop
    //   77: aload_3
    //   78: aload_0
    //   79: getfield 15	dyh:e	Ljava/lang/String;
    //   82: invokevirtual 80	bfz:M	(Ljava/lang/String;)J
    //   85: lstore_1
    //   86: new 82	edp
    //   89: dup
    //   90: aload_0
    //   91: getfield 15	dyh:e	Ljava/lang/String;
    //   94: aload_0
    //   95: getfield 64	dyx:b	Ldvb;
    //   98: getfield 85	dvb:b	Lbfd;
    //   101: invokevirtual 90	bfd:b	()Lczb;
    //   104: lload_1
    //   105: ldc2_w 91
    //   108: aload 4
    //   110: aconst_null
    //   111: aload_0
    //   112: getfield 17	dyh:a	I
    //   115: getstatic 97	emc:b	Lemc;
    //   118: invokespecial 100	edp:<init>	(Ljava/lang/String;Lczb;JJLjava/lang/String;Ljava/lang/String;ILemc;)V
    //   121: aload_3
    //   122: invokevirtual 103	edp:b	(Lbfz;)V
    //   125: aload_3
    //   126: invokevirtual 105	bfz:b	()V
    //   129: aload_3
    //   130: invokevirtual 108	bfz:c	()V
    //   133: aload_0
    //   134: getfield 15	dyh:e	Ljava/lang/String;
    //   137: invokestatic 111	bfz:a	(Ljava/lang/String;)Z
    //   140: ifne +24 -> 164
    //   143: aload_0
    //   144: new 113	bvm
    //   147: dup
    //   148: aload 4
    //   150: aload_0
    //   151: getfield 15	dyh:e	Ljava/lang/String;
    //   154: aload_0
    //   155: getfield 17	dyh:a	I
    //   158: invokespecial 116	bvm:<init>	(Ljava/lang/String;Ljava/lang/String;I)V
    //   161: invokevirtual 119	dyh:a	(Leff;)V
    //   164: aload_3
    //   165: aload_0
    //   166: getfield 15	dyh:e	Ljava/lang/String;
    //   169: invokestatic 125	bft:d	(Lbfz;Ljava/lang/String;)V
    //   172: return
    //   173: new 29	java/lang/String
    //   176: dup
    //   177: ldc 39
    //   179: invokespecial 128	java/lang/String:<init>	(Ljava/lang/String;)V
    //   182: astore_3
    //   183: goto -152 -> 31
    //   186: astore 4
    //   188: aload_3
    //   189: invokevirtual 108	bfz:c	()V
    //   192: aload 4
    //   194: athrow
    // Local variable table:
    //   start	length	slot	name	signature
    //   0	195	0	this	dyh
    //   85	20	1	l	long
    //   16	173	3	localObject1	Object
    //   44	105	4	str	String
    //   186	7	4	localObject2	Object
    // Exception table:
    //   from	to	target	type
    //   68	129	186	finally
  }
}

/* Location:
 * Qualified Name:     dyh
 * Java Class Version: 6 (50.0)
 * JD-Core Version:    0.7.1
 */