final class eiv
  implements Runnable
{
  eiv(eit parameit, ejc paramejc, byte[] paramArrayOfByte, eis parameis) {}
  
  /* Error */
  public void run()
  {
    // Byte code:
    //   0: getstatic 34	eit:b	Lezv;
    //   3: ldc 36
    //   5: invokevirtual 41	ezv:b	(Ljava/lang/String;)Ljava/lang/String;
    //   8: pop
    //   9: getstatic 44	eit:a	Z
    //   12: ifeq +38 -> 50
    //   15: aload_0
    //   16: getfield 18	eiv:d	Leit;
    //   19: astore_2
    //   20: aload_0
    //   21: getfield 20	eiv:a	Lejc;
    //   24: invokevirtual 50	ejc:toString	()Ljava/lang/String;
    //   27: invokestatic 56	java/lang/String:valueOf	(Ljava/lang/Object;)Ljava/lang/String;
    //   30: astore_1
    //   31: aload_1
    //   32: invokevirtual 60	java/lang/String:length	()I
    //   35: ifeq +47 -> 82
    //   38: ldc 62
    //   40: aload_1
    //   41: invokevirtual 65	java/lang/String:concat	(Ljava/lang/String;)Ljava/lang/String;
    //   44: astore_1
    //   45: aload_2
    //   46: aload_1
    //   47: invokevirtual 69	eit:e	(Ljava/lang/String;)V
    //   50: aload_0
    //   51: getfield 18	eiv:d	Leit;
    //   54: aload_0
    //   55: getfield 22	eiv:b	[B
    //   58: aload_0
    //   59: getfield 24	eiv:c	Leis;
    //   62: invokevirtual 73	eis:b	()Ljava/lang/String;
    //   65: aload_0
    //   66: getfield 20	eiv:a	Lejc;
    //   69: iconst_1
    //   70: invokestatic 76	eit:a	(Leit;[BLjava/lang/String;Lejc;Z)V
    //   73: getstatic 34	eit:b	Lezv;
    //   76: ldc 36
    //   78: invokevirtual 78	ezv:c	(Ljava/lang/String;)V
    //   81: return
    //   82: new 52	java/lang/String
    //   85: dup
    //   86: ldc 62
    //   88: invokespecial 80	java/lang/String:<init>	(Ljava/lang/String;)V
    //   91: astore_1
    //   92: goto -47 -> 45
    //   95: astore_1
    //   96: getstatic 34	eit:b	Lezv;
    //   99: ldc 36
    //   101: invokevirtual 78	ezv:c	(Ljava/lang/String;)V
    //   104: aload_1
    //   105: athrow
    // Local variable table:
    //   start	length	slot	name	signature
    //   0	106	0	this	eiv
    //   30	62	1	str	String
    //   95	10	1	localObject	Object
    //   19	27	2	localeit	eit
    // Exception table:
    //   from	to	target	type
    //   0	45	95	finally
    //   45	50	95	finally
    //   50	73	95	finally
    //   82	92	95	finally
  }
}

/* Location:
 * Qualified Name:     eiv
 * Java Class Version: 6 (50.0)
 * JD-Core Version:    0.7.1
 */