import java.util.ArrayList;

public class gpn
{
  private final String a;
  private final ArrayList<Long> b = new ArrayList();
  private final ArrayList<String> c = new ArrayList();
  
  public gpn(String paramString)
  {
    a = paramString;
    a("");
  }
  
  public void a(String paramString)
  {
    try
    {
      b.add(Long.valueOf(System.currentTimeMillis()));
      c.add(paramString);
      return;
    }
    finally
    {
      paramString = finally;
      throw paramString;
    }
  }
  
  /* Error */
  public void b(String paramString)
  {
    // Byte code:
    //   0: aload_0
    //   1: monitorenter
    //   2: aload_0
    //   3: ldc 27
    //   5: invokevirtual 29	gpn:a	(Ljava/lang/String;)V
    //   8: aload_0
    //   9: getfield 21	gpn:b	Ljava/util/ArrayList;
    //   12: iconst_0
    //   13: invokevirtual 50	java/util/ArrayList:get	(I)Ljava/lang/Object;
    //   16: checkcast 38	java/lang/Long
    //   19: invokevirtual 53	java/lang/Long:longValue	()J
    //   22: lstore_3
    //   23: aload_0
    //   24: getfield 21	gpn:b	Ljava/util/ArrayList;
    //   27: aload_0
    //   28: getfield 21	gpn:b	Ljava/util/ArrayList;
    //   31: invokevirtual 57	java/util/ArrayList:size	()I
    //   34: iconst_1
    //   35: isub
    //   36: invokevirtual 50	java/util/ArrayList:get	(I)Ljava/lang/Object;
    //   39: checkcast 38	java/lang/Long
    //   42: invokevirtual 53	java/lang/Long:longValue	()J
    //   45: lstore 5
    //   47: lload 5
    //   49: lload_3
    //   50: lsub
    //   51: lstore 5
    //   53: lload 5
    //   55: lconst_0
    //   56: lcmp
    //   57: ifge +6 -> 63
    //   60: aload_0
    //   61: monitorexit
    //   62: return
    //   63: invokestatic 62	gpd:a	()Ljava/lang/StringBuilder;
    //   66: astore_1
    //   67: aload_1
    //   68: aload_0
    //   69: getfield 25	gpn:a	Ljava/lang/String;
    //   72: invokevirtual 68	java/lang/StringBuilder:append	(Ljava/lang/String;)Ljava/lang/StringBuilder;
    //   75: pop
    //   76: aload_1
    //   77: ldc 70
    //   79: invokevirtual 68	java/lang/StringBuilder:append	(Ljava/lang/String;)Ljava/lang/StringBuilder;
    //   82: pop
    //   83: aload_1
    //   84: lload 5
    //   86: invokevirtual 73	java/lang/StringBuilder:append	(J)Ljava/lang/StringBuilder;
    //   89: pop
    //   90: aload_1
    //   91: ldc 75
    //   93: invokevirtual 68	java/lang/StringBuilder:append	(Ljava/lang/String;)Ljava/lang/StringBuilder;
    //   96: pop
    //   97: iconst_1
    //   98: istore_2
    //   99: iload_2
    //   100: aload_0
    //   101: getfield 21	gpn:b	Ljava/util/ArrayList;
    //   104: invokevirtual 57	java/util/ArrayList:size	()I
    //   107: if_icmpge +68 -> 175
    //   110: aload_0
    //   111: getfield 21	gpn:b	Ljava/util/ArrayList;
    //   114: iload_2
    //   115: invokevirtual 50	java/util/ArrayList:get	(I)Ljava/lang/Object;
    //   118: checkcast 38	java/lang/Long
    //   121: invokevirtual 53	java/lang/Long:longValue	()J
    //   124: lstore 5
    //   126: aload_1
    //   127: aload_0
    //   128: getfield 23	gpn:c	Ljava/util/ArrayList;
    //   131: iload_2
    //   132: invokevirtual 50	java/util/ArrayList:get	(I)Ljava/lang/Object;
    //   135: checkcast 77	java/lang/String
    //   138: invokevirtual 68	java/lang/StringBuilder:append	(Ljava/lang/String;)Ljava/lang/StringBuilder;
    //   141: pop
    //   142: aload_1
    //   143: ldc 70
    //   145: invokevirtual 68	java/lang/StringBuilder:append	(Ljava/lang/String;)Ljava/lang/StringBuilder;
    //   148: pop
    //   149: aload_1
    //   150: lload 5
    //   152: lload_3
    //   153: lsub
    //   154: invokevirtual 73	java/lang/StringBuilder:append	(J)Ljava/lang/StringBuilder;
    //   157: pop
    //   158: aload_1
    //   159: ldc 79
    //   161: invokevirtual 68	java/lang/StringBuilder:append	(Ljava/lang/String;)Ljava/lang/StringBuilder;
    //   164: pop
    //   165: iload_2
    //   166: iconst_1
    //   167: iadd
    //   168: istore_2
    //   169: lload 5
    //   171: lstore_3
    //   172: goto -73 -> 99
    //   175: iconst_2
    //   176: invokestatic 85	aal:q	(I)Z
    //   179: pop
    //   180: goto -120 -> 60
    //   183: astore_1
    //   184: aload_0
    //   185: monitorexit
    //   186: aload_1
    //   187: athrow
    // Local variable table:
    //   start	length	slot	name	signature
    //   0	188	0	this	gpn
    //   0	188	1	paramString	String
    //   98	71	2	i	int
    //   22	150	3	l1	long
    //   45	125	5	l2	long
    // Exception table:
    //   from	to	target	type
    //   2	47	183	finally
    //   63	97	183	finally
    //   99	165	183	finally
    //   175	180	183	finally
  }
}

/* Location:
 * Qualified Name:     gpn
 * Java Class Version: 6 (50.0)
 * JD-Core Version:    0.7.1
 */